robocorp/_meta/__init__.py
robocorp/_meta/py.typed
robocorp-2.1.3.dist-info/METADATA
robocorp-2.1.3.dist-info/WHEEL
robocorp-2.1.3.dist-info/RECORD
