Metadata-Version: 2.1
Name: robocorp
Version: 2.1.3
Summary: Robocorp core libraries for Python automation
Home-page: https://github.com/robocorp/robocorp/
License: Apache-2.0
Author: Fabio Z.
Author-email: fabio@robocorp.com
Requires-Python: >3.9.1,<4.0
Classifier: License :: OSI Approved :: Apache Software License
Classifier: Programming Language :: Python :: 3
Classifier: Programming Language :: Python :: 3.10
Classifier: Programming Language :: Python :: 3.11
Classifier: Programming Language :: Python :: 3.12
Requires-Dist: robocorp-log (>=2.9.6,<3.0.0)
Requires-Dist: robocorp-storage (>=1.0.4,<2.0.0)
Requires-Dist: robocorp-tasks (>=3.1.1,<4.0.0)
Requires-Dist: robocorp-vault (>=1.3.8,<2.0.0)
Requires-Dist: robocorp-workitems (>=1.4.5,<2.0.0)
Project-URL: Repository, https://github.com/robocorp/robocorp/
